<pkgref spec="1.12" uuid="FF733F58-BECE-4C8C-958E-865C398C4C40"><config><identifier>com.2sprout.2sproutOsX.2sproutclient.pkg</identifier><version>1</version><description/><post-install type="none"/><requireAuthorization/><installFrom>/Users/jonathandrosdeck/Desktop/2sprout/Standard UDP/Client/2sproutClient</installFrom><installTo mod="true">/usr/lib/</installTo><flags><followSymbolicLinks/></flags><packageStore type="internal"/><mod>parent</mod><mod>installTo.path</mod><mod>installTo</mod></config><contents><file-list>012sproutclient-contents.xml</file-list><filter>/CVS$</filter><filter>/\.svn$</filter><filter>/\.cvsignore$</filter><filter>/\.cvspass$</filter><filter>/\.DS_Store$</filter></contents></pkgref>